algorithms_extensions/__init__.py
algorithms_extensions/loadable.py
algorithms_extensions/opencv_model.py
algorithms_extensions/descriptors/__init__.py
algorithms_extensions/descriptors/descriptor_mxnet.py
algorithms_extensions/descriptors/tf_unfreezed.py
mnd_algorithms_extensions-0.1.1.dist-info/LICENSE
mnd_algorithms_extensions-0.1.1.dist-info/METADATA
mnd_algorithms_extensions-0.1.1.dist-info/WHEEL
mnd_algorithms_extensions-0.1.1.dist-info/top_level.txt
mnd_algorithms_extensions-0.1.1.dist-info/RECORD
