Metadata-Version: 2.1
Name: mnd-algorithms-extensions
Version: 0.1.1
Summary: Utility classes that complement the mnd-algorithms package
Home-page: https://github.com/mnicolas94/algorithms-extensions
Author: Miguel Nicolás-Díaz
Author-email: miguelcok27@gmail.com
License: UNKNOWN
Platform: UNKNOWN
Classifier: Programming Language :: Python :: 3
Classifier: License :: OSI Approved :: MIT License
Classifier: Operating System :: OS Independent
Classifier: Development Status :: 3 - Alpha
Classifier: Intended Audience :: Developers
Requires-Python: >=3.6
License-File: LICENSE
Requires-Dist: mnd-algorithms
Requires-Dist: easydict
